Metadata-Version: 2.1
Name: EmailUpdate
Version: 0.0.0
Summary: Package to Add Email Updates to Code
Home-page: https://github.com/dschlesinger/EmailMe
Author: Denali Schlesinger
Author-email: dsch28@bu.edu
Classifier: Programming Language :: Python :: 3
Classifier: License :: OSI Approved :: MIT License
Classifier: Operating System :: OS Independent
Requires-Python: >=3.5
